paypal_client/__init__.py
paypal_client/api.py
paypal_client/exceptions.py
paypal_rest_api-0.1.7.dist-info/licenses/LICENSE
paypal_rest_api-0.1.7.dist-info/METADATA
paypal_rest_api-0.1.7.dist-info/WHEEL
paypal_rest_api-0.1.7.dist-info/top_level.txt
paypal_rest_api-0.1.7.dist-info/RECORD
