Metadata-Version: 2.4
Name: paypal-rest-api
Version: 0.1.7
Summary: PayPal API provides simple client for RESTful APIs
Author-email: Kalinin Mitko <kalinin.mitko@gmail.com>
License: MIT License
Project-URL: Homepage, https://github.com/null-none/paypal-rest-api
Keywords: python,paypal,api,rest api
Classifier: License :: OSI Approved :: MIT License
Classifier: Programming Language :: Python
Classifier: Programming Language :: Python :: 3
Requires-Python: >=3.9
License-File: LICENSE
Provides-Extra: dev
Requires-Dist: pip-tools; extra == "dev"
Dynamic: license-file
